laser/__init__.py
laser/__main__.py
laser/data.py
laser/encoder.py
laser/generator_utils.py
laser/pretrained.py
laser/sent_encoder.py
laser/utils.py
laser/bin/__init__.py
laser/bin/encode_texts.py
laser/bin/filter_parallel.py
laser_keep_alive-1.0.0.dist-info/LICENSE
laser_keep_alive-1.0.0.dist-info/METADATA
laser_keep_alive-1.0.0.dist-info/WHEEL
laser_keep_alive-1.0.0.dist-info/top_level.txt
laser_keep_alive-1.0.0.dist-info/RECORD
