Metadata-Version: 2.1
Name: laser-keep-alive
Version: 1.0.0
Summary: Keeping the original LASER project alive
Home-page: https://github.com/mingruimingrui/laser-keep-alive
Author: Wang Ming Rui
Author-email: mingruimingrui@hotmail.com
License: MIT
Keywords: laser sentence embedding
Platform: UNKNOWN
Classifier: License :: OSI Approved :: MIT License
Classifier: Intended Audience :: Developers
Classifier: Intended Audience :: Education
Classifier: Intended Audience :: Science/Research
Classifier: Programming Language :: Python :: 3
Classifier: Programming Language :: Python :: 3.6
Classifier: Programming Language :: Python :: 3.7
Classifier: Programming Language :: Python :: 3.8
Classifier: Topic :: Scientific/Engineering
Classifier: Topic :: Scientific/Engineering :: Mathematics
Classifier: Topic :: Scientific/Engineering :: Artificial Intelligence
Classifier: Topic :: Software Development
Classifier: Topic :: Software Development :: Libraries
Classifier: Topic :: Software Development :: Libraries :: Python Modules
Requires-Python: >=3.6.1
Requires-Dist: tqdm (>=4.0)
Requires-Dist: Cython (>=0.29.6)
Requires-Dist: torch (>=1.0)
Requires-Dist: fastBPE (==0.1.0)
Requires-Dist: mosestokenizer (==1.1.0)
Requires-Dist: jieba (==0.39)
Requires-Dist: opencc-python-reimplemented (==0.1.5)
Requires-Dist: transliterate (==1.10.2)
Requires-Dist: mecab-python3 (==0.996.5)
Requires-Dist: pandas (>=1.0)
